flask_accept/__init__.py
flask_accept-0.0.7.dist-info/LICENSE
flask_accept-0.0.7.dist-info/METADATA
flask_accept-0.0.7.dist-info/WHEEL
flask_accept-0.0.7.dist-info/top_level.txt
flask_accept-0.0.7.dist-info/RECORD
